{
	"configurations" : 
	[
		{
			"directories" : 
			[
				{
					"build" : ".",
					"hasInstallRule" : true,
					"minimumCMakeVersion" : 
					{
						"string" : "3.5"
					},
					"projectIndex" : 0,
					"source" : ".",
					"targetIndexes" : 
					[
						0,
						1,
						2
					]
				}
			],
			"name" : "",
			"projects" : 
			[
				{
					"directoryIndexes" : 
					[
						0
					],
					"name" : "lab_2",
					"targetIndexes" : 
					[
						0,
						1,
						2
					]
				}
			],
			"targets" : 
			[
				{
					"directoryIndex" : 0,
					"id" : "lab_2_uninstall::@6890427a1f51a3e7e1df",
					"jsonFile" : "target-lab_2_uninstall-4451ea9db693b00a1be7.json",
					"name" : "lab_2_uninstall",
					"projectIndex" : 0
				},
				{
					"directoryIndex" : 0,
					"id" : "robot_control::@6890427a1f51a3e7e1df",
					"jsonFile" : "target-robot_control-50b0e2615ff03e288cb1.json",
					"name" : "robot_control",
					"projectIndex" : 0
				},
				{
					"directoryIndex" : 0,
					"id" : "uninstall::@6890427a1f51a3e7e1df",
					"jsonFile" : "target-uninstall-46a2d12f74bcb2533c58.json",
					"name" : "uninstall",
					"projectIndex" : 0
				}
			]
		}
	],
	"kind" : "codemodel",
	"paths" : 
	{
		"build" : "/home/gentleshaz/ros2_ws/l2/build/lab_2",
		"source" : "/home/gentleshaz/ros2_ws/l2/src/lab_2"
	},
	"version" : 
	{
		"major" : 2,
		"minor" : 0
	}
}
